libname/__init__.py
libname/nqueen.py
practicalexam-0.0.4.dist-info/METADATA
practicalexam-0.0.4.dist-info/WHEEL
practicalexam-0.0.4.dist-info/top_level.txt
practicalexam-0.0.4.dist-info/RECORD
