Metadata-Version: 2.1
Name: practicalexam
Version: 0.0.4
Summary: practical exam
Author: AK
Author-email: <arkenkumar@gmail.com>
Keywords: python,video,stream,video stream,camera stream,sockets
